unacatlib/__init__.py
unacatlib/address_component.py
unacatlib/address_component_builder.py
unacatlib/catalog.py
unacatlib/client.py
unacatlib/dimension.py
unacatlib/dimension_builder.py
unacatlib/filter.py
unacatlib/index_job.py
unacatlib/layer.py
unacatlib/layer_builder.py
unacatlib/layer_series.py
unacatlib/metric.py
unacatlib/metric_builder.py
unacatlib/query_client.py
unacatlib/byo/__init__.py
unacatlib/byo/byo_orchestator.py
unacatlib/byo_external/__init__.py
unacatlib/byo_external/client.py
unacatlib/byo_external/metric_status.py
unacatlib/byo_external/report_job.py
unacatlib/query/__init__.py
unacatlib/query/data_reference_list_plugin.py
unacatlib/query/field_definition_list_plugin.py
unacatlib/query/proto_wrappers.py
unacatlib/query/record_list_plugin.py
unacatlib/query/record_statistics_list_plugin.py
unacatlib/query/text_utils.py
unacatlib/query/values_list_plugin.py
unacatlib/unacast/__init__.py
unacatlib/unacast/access/__init__.py
unacatlib/unacast/access/v1/__init__.py
unacatlib/unacast/analyticsexport/__init__.py
unacatlib/unacast/analyticsexport/v1/__init__.py
unacatlib/unacast/byo/__init__.py
unacatlib/unacast/byo/v1/__init__.py
unacatlib/unacast/catalog/__init__.py
unacatlib/unacast/catalog/v1/__init__.py
unacatlib/unacast/catalog/v3/__init__.py
unacatlib/unacast/catalog/v3alpha/__init__.py
unacatlib/unacast/dataset/__init__.py
unacatlib/unacast/dataset/v1/__init__.py
unacatlib/unacast/iam/__init__.py
unacatlib/unacast/iam/v1/__init__.py
unacatlib/unacast/index/__init__.py
unacatlib/unacast/index/v1/__init__.py
unacatlib/unacast/maps/__init__.py
unacatlib/unacast/maps/v1/__init__.py
unacatlib/unacast/metric/__init__.py
unacatlib/unacast/metric/v1/__init__.py
unacatlib/unacast/metricmodel/__init__.py
unacatlib/unacast/metricmodel/v1/__init__.py
unacatlib/unacast/operator/__init__.py
unacatlib/unacast/operator/v1/__init__.py
unacatlib/unacast/subscription/__init__.py
unacatlib/unacast/subscription/v1/__init__.py
unacatlib/unacast/system/__init__.py
unacatlib-0.0.93.dist-info/METADATA
unacatlib-0.0.93.dist-info/WHEEL
unacatlib-0.0.93.dist-info/top_level.txt
unacatlib-0.0.93.dist-info/RECORD
