Metadata-Version: 2.4
Name: unacatlib
Version: 0.0.93
Summary: Unacat Python client
Home-page: http://github.com/unacast/unacat
License: MIT
Requires-Dist: grpcio>=1.40.0
Requires-Dist: grpcio-tools>=1.40.0
Requires-Dist: grpclib>=0.4.5
Requires-Dist: pandas>=1.3.0
Requires-Dist: betterproto[compiler]>=2.0.0b5
Requires-Dist: syncer>=1.3.0
Requires-Dist: nest_asyncio>=1.5.6
Requires-Dist: halo>=0.0.31
Requires-Dist: geojson>=2.5.0
Provides-Extra: docs
Requires-Dist: sphinx>=4.0.0; extra == "docs"
Requires-Dist: sphinx-rtd-theme; extra == "docs"
Requires-Dist: sphinx-autodoc-typehints; extra == "docs"
Dynamic: home-page
Dynamic: license
Dynamic: provides-extra
Dynamic: requires-dist
Dynamic: summary
